pypp_cli/cli.py
pypp_cli/data/cpp_template/.clang-format
pypp_cli/data/cpp_template/pypp/py_dict.h
pypp_cli/data/cpp_template/pypp/py_dict_default.h
pypp_cli/data/cpp_template/pypp/py_enumerate.h
pypp_cli/data/cpp_template/pypp/py_list.h
pypp_cli/data/cpp_template/pypp/py_range.h
pypp_cli/data/cpp_template/pypp/py_reversed.h
pypp_cli/data/cpp_template/pypp/py_set.h
pypp_cli/data/cpp_template/pypp/py_str.cpp
pypp_cli/data/cpp_template/pypp/py_str.h
pypp_cli/data/cpp_template/pypp/py_tuple.h
pypp_cli/data/cpp_template/pypp/py_zip.h
pypp_cli/data/cpp_template/pypp/pypp_assert.h
pypp_cli/data/cpp_template/pypp/pypp_os.cpp
pypp_cli/data/cpp_template/pypp/pypp_os.h
pypp_cli/data/cpp_template/pypp/pypp_platform.cpp
pypp_cli/data/cpp_template/pypp/pypp_platform.h
pypp_cli/data/cpp_template/pypp/pypp_random.cpp
pypp_cli/data/cpp_template/pypp/pypp_random.h
pypp_cli/data/cpp_template/pypp/pypp_resources.cpp
pypp_cli/data/cpp_template/pypp/pypp_resources.h
pypp_cli/data/cpp_template/pypp/pypp_shutil.h
pypp_cli/data/cpp_template/pypp/pypp_text_io.cpp
pypp_cli/data/cpp_template/pypp/pypp_text_io.h
pypp_cli/data/cpp_template/pypp/pypp_time.h
pypp_cli/data/cpp_template/pypp/pypp_union.h
pypp_cli/data/cpp_template/pypp/exceptions/common.cpp
pypp_cli/data/cpp_template/pypp/exceptions/common.h
pypp_cli/data/cpp_template/pypp/exceptions/exception.cpp
pypp_cli/data/cpp_template/pypp/exceptions/exception.h
pypp_cli/data/cpp_template/pypp/exceptions/filesystem.cpp
pypp_cli/data/cpp_template/pypp/exceptions/filesystem.h
pypp_cli/data/cpp_template/pypp/pypp_util/escape_special.cpp
pypp_cli/data/cpp_template/pypp/pypp_util/escape_special.h
pypp_cli/data/cpp_template/pypp/pypp_util/floor_div.cpp
pypp_cli/data/cpp_template/pypp/pypp_util/floor_div.h
pypp_cli/data/cpp_template/pypp/pypp_util/generator.h
pypp_cli/data/cpp_template/pypp/pypp_util/main_error_handler.cpp
pypp_cli/data/cpp_template/pypp/pypp_util/main_error_handler.h
pypp_cli/data/cpp_template/pypp/pypp_util/math.h
pypp_cli-0.0.2.dist-info/METADATA
pypp_cli-0.0.2.dist-info/WHEEL
pypp_cli-0.0.2.dist-info/entry_points.txt
pypp_cli-0.0.2.dist-info/licenses/LICENSE
pypp_cli-0.0.2.dist-info/RECORD
