Metadata-Version: 2.4
Name: pypp-cli
Version: 0.0.2
Summary: The CLI tool for the Py++ project
Project-URL: Homepage, https://github.com/curtispuetz/pypp-cli
Author-email: Curtis Puetz <pypp.main@yahoo.com>
License: MIT
License-File: LICENSE
Requires-Python: >=3.13
Requires-Dist: pydantic==2.11.9
